k2eg/__init__.py
k2eg/__main__.py
k2eg/__version__.py
k2eg/broker.py
k2eg/dml.py
k2eg/serialization.py
k2eg/cli/__init__.py
k2eg/cli/__main__.py
k2eg/cli/get.py
k2eg/cli/monitor.py
k2eg/cli/put.py
k2eg-0.2.20.dist-info/METADATA
k2eg-0.2.20.dist-info/WHEEL
k2eg-0.2.20.dist-info/entry_points.txt
k2eg-0.2.20.dist-info/top_level.txt
k2eg-0.2.20.dist-info/RECORD
