Metadata-Version: 2.4
Name: k2eg
Version: 0.2.20
Summary: A k2eg library
Author-email: Claudio Bisegni <bisegni@slac.stanford.edu>
Classifier: Development Status :: 3 - Alpha
Classifier: Intended Audience :: Developers
Classifier: License :: OSI Approved :: MIT License
Classifier: Programming Language :: Python :: 3
Requires-Dist: shellingham
Requires-Dist: confluent-kafka
Requires-Dist: python_snappy
Requires-Dist: rich
Requires-Dist: msgpack
Requires-Dist: dynaconf
Requires-Dist: readerwriterlock
Requires-Dist: python-dotenv
Requires-Dist: click
Requires-Dist: click-loglevel
Requires-Dist: wheel
Requires-Dist: setuptools
Requires-Dist: click_repl
